convection/plugins/secrets/passdb.py
convection/plugins/secrets/specs/passdb.config.spec
convection/plugins/secrets/specs/plugin.secret.passdb.spec
convection_plugin_secrets_passdb-1.0.0.dist-info/LICENSE.md
convection_plugin_secrets_passdb-1.0.0.dist-info/METADATA
convection_plugin_secrets_passdb-1.0.0.dist-info/WHEEL
convection_plugin_secrets_passdb-1.0.0.dist-info/top_level.txt
convection_plugin_secrets_passdb-1.0.0.dist-info/RECORD
