Metadata-Version: 2.1
Name: convection-plugin-secrets-passdb
Version: 1.0.0
Summary: Convection Secrets Store Plugin for Password Generation and Storage
Author-email: AccidentallyTheCable <cableninja@cableninja.net>
License: GPLv3
Project-URL: Homepage, https://gitlab.com/accidentallythecable-public/convection-suite/plugins/secrets/passdb/
Project-URL: Bug Tracker, https://gitlab.com/accidentallythecable-public/convection-suite/plugins/secrets/passdb/issues
Classifier: Programming Language :: Python :: 3
Classifier: License :: OSI Approved :: GNU General Public License v3 (GPLv3)
Classifier: Environment :: Plugins
Classifier: Operating System :: POSIX
Classifier: Topic :: Communications
Classifier: Topic :: Utilities
Requires-Python: >=3.9
License-File: LICENSE.md
Requires-Dist: convection-shared <=1.0
